LICENSE
MANIFEST.in
README.md
requirements.txt
setup.cfg
setup.py
pylightcurve/__author__.txt
pylightcurve/__author_email__.txt
pylightcurve/__databases__.pickle
pylightcurve/__databases__.py
pylightcurve/__description__.txt
pylightcurve/__init__.py
pylightcurve/__url__.txt
pylightcurve/__version__.txt
pylightcurve/errors.py
pylightcurve.egg-info/PKG-INFO
pylightcurve.egg-info/SOURCES.txt
pylightcurve.egg-info/dependency_links.txt
pylightcurve.egg-info/not-zip-safe
pylightcurve.egg-info/requires.txt
pylightcurve.egg-info/top_level.txt
pylightcurve/analysis/__init__.py
pylightcurve/analysis/curve_fit.py
pylightcurve/analysis/distributions.py
pylightcurve/analysis/gaussian.py
pylightcurve/analysis/numerical_integration.py
pylightcurve/analysis/optimisation.py
pylightcurve/catalogues/__init__.py
pylightcurve/catalogues/catalogues.py
pylightcurve/images/__init__.py
pylightcurve/images/find_stars.py
pylightcurve/models/__init__.py
pylightcurve/models/exoplanet.py
pylightcurve/models/exoplanet_lc.py
pylightcurve/plots/__init__.py
pylightcurve/plots/plots_fitting.py
pylightcurve/processes/__init__.py
pylightcurve/processes/counter.py
pylightcurve/processes/files.py
pylightcurve/spacetime/__init__.py
pylightcurve/spacetime/angles.py
pylightcurve/spacetime/targets.py
tests/test_analysis_distributions.py
tests/test_analysis_gaussian.py
tests/test_analysis_optimisation.py
tests/test_catalogues.py
tests/test_images_find_stars.py
tests/test_models_exoplanet.py
tests/test_models_exoplanet_lc.py
tests/test_processes_files.py
tests/test_spacetime_angles.py
tests/test_spacetime_targets.py